mammut_pytorch/__init__.py
mammut_pytorch/mammut_pytorch.py
MaMMUT_pytorch-0.0.7.dist-info/LICENSE
MaMMUT_pytorch-0.0.7.dist-info/METADATA
MaMMUT_pytorch-0.0.7.dist-info/WHEEL
MaMMUT_pytorch-0.0.7.dist-info/top_level.txt
MaMMUT_pytorch-0.0.7.dist-info/RECORD
