Metadata-Version: 2.1
Name: MaMMUT-pytorch
Version: 0.0.7
Summary: MaMMUT - Pytorch
Home-page: https://github.com/lucidrains/MaMMUT-pytorch
Author: Phil Wang
Author-email: lucidrains@gmail.com
License: MIT
Keywords: artificial intelligence,deep learning,multimodal,attention mechanism,contrastive learning
Classifier: Development Status :: 4 - Beta
Classifier: Intended Audience :: Developers
Classifier: Topic :: Scientific/Engineering :: Artificial Intelligence
Classifier: License :: OSI Approved :: MIT License
Classifier: Programming Language :: Python :: 3.6
License-File: LICENSE
Requires-Dist: einops >=0.6.1
Requires-Dist: torch >=1.6
